drf_nested_multipart_parser/__init__.py
drf_nested_multipart_parser/parser.py
drf_nested_multipart_parser-0.0.2.dist-info/LICENSE
drf_nested_multipart_parser-0.0.2.dist-info/METADATA
drf_nested_multipart_parser-0.0.2.dist-info/WHEEL
drf_nested_multipart_parser-0.0.2.dist-info/top_level.txt
drf_nested_multipart_parser-0.0.2.dist-info/RECORD
