Metadata-Version: 2.1
Name: drf-nested-multipart-parser
Version: 0.0.2
Summary: Parser for nested params in multipart file upload
Home-page: https://github.com/mick912/drf_nested_mutipart_parser.git
Author: Mirjan Asymbaev
Author-email: mirjan.asymbaev@gmail.com
License: MIT
Platform: UNKNOWN
Classifier: Environment :: Web Environment
Classifier: Framework :: Django
Classifier: Intended Audience :: Developers
Classifier: Programming Language :: Python
Classifier: Programming Language :: Python :: 3
Classifier: Topic :: Internet :: WWW/HTTP
Classifier: License :: OSI Approved :: MIT License
Requires-Python: >=3.6
